{
	"ID": "rItSEbaEEgLX",
	"Title": "木材市價單一樹種報表",
	"Organ": "林務局",
	"Catalog": "造林生產",
	"Counter": 6936,
	"Lnkcnt": 667,
	"LastUpdateTime": "2020-01-14",
	"Messages": 0,
	"Collect": 0,
	"rating": "3",
	"NumberOfVoters": "0",
	"UpdateFrequency": "每月",
	"description": "提供資料包含:民國年份、查詢月份、產地、材別、樹種名稱、品等名稱、規格、單位、羅東處價格、新竹處價格、東勢處價格、南投處價格、嘉義處價格、屏東處價格、臺東處價格、花蓮處價格等欄位資料。",
	"sourceURL": "http://woodprice.forest.gov.tw/Summary/Q_SummarySingleWoodPrice.aspx",
	"interfaceURL": "https://data.coa.gov.tw/Service/OpenData/TransService.aspx?UnitId=rItSEbaEEgLX"
}